MANIFEST.in
README.md
setup.py
djangocms_panel/__init__.py
djangocms_panel/cms_plugins.py
djangocms_panel/models.py
djangocms_panel.egg-info/PKG-INFO
djangocms_panel.egg-info/SOURCES.txt
djangocms_panel.egg-info/dependency_links.txt
djangocms_panel.egg-info/not-zip-safe
djangocms_panel.egg-info/top_level.txt
djangocms_panel/migrations/0001_initial.py
djangocms_panel/migrations/__init__.py
djangocms_panel/templates/djangocms_panel/panel.html