Metadata-Version: 1.1
Name: djangocms-panel
Version: 1.0.0
Summary: Bootstrap panel plugin for Django-CMS
Home-page: https://github.com/tsbarnes/djangocms-panel
Author: T. Scott Barnes
Author-email: barnes.t.scott@gmail.com
License: LICENSE.txt
Platform: OS Independent
Classifier: Development Status :: 5 - Production/Stable
Classifier: Environment :: Web Environment
Classifier: Framework :: Django
Classifier: Intended Audience :: Developers
Classifier: License :: OSI Approved :: BSD License
Classifier: Operating System :: OS Independent
Classifier: Programming Language :: Python
Classifier: Topic :: Communications
Classifier: Topic :: Internet :: WWW/HTTP :: Dynamic Content
Classifier: Programming Language :: Python :: 2.7
